{"paths":{},"types":[],"uuids":["03joUzlW9NVqtuPnrDn8x9","3eMjgYM1ZBH4ICbzxiZAix","54buymS95EjZ/ELrJ8IbGh","71VhFCTINJM6/Ky3oX9nBT","94cjw0PpBPB5hLxW8CJh/K","b4P/PCArtIdIH38t6mlw8Y","e8Ueib+qJEhL6mXAHdnwbi","0dpVWJbxtLI5GHwwiDc0kQ","1ajP/vjJBIOq71NMhdFDxR","20TDbVnoVLz50XKOLGjFKa","29FYIk+N1GYaeWH/q1NxQO","4cP7okYztLHaaSFYULOhY6","51G5LYxWJGVqCAWXGZ9qwB","7cHDXRDfZI+JIjkWBp9UEQ","c1mXLhXABN06XcKUWORzrj","d9RZW2NXBE3Je+OM6+WyfE","d9ZSkMv7FA0JwxW/SnHo5r","e1mtNtuvxGAaUmx4CPA605","e97GVMl6JHh5Ml5qEDdSGa","ecpdLyjvZBwrvm+cedCcQy","efvnLV839LQKLjUxx/rLGc","f0BIwQ8D5Ml7nTNQbh1YlS","f9ThKhTA5Obpchz+dVNIFC"],"scenes":{"db://assets/scene/scene.fire":1},"redirect":[19,0],"deps":["internal"],"packs":{"0cc730d51":[0,2,3,4,5,6],"0e9a8fccd":[7,8,9,10,1,11,12,13,14,15,16,17,18,20,21,22]},"name":"main","importBase":"import","nativeBase":"native","debug":false,"isZip":false,"encrypted":true,"versions":{"import":["0cc730d51","3ee0b","0e9a8fccd","4106a"],"native":[0,"5cd64",2,"d8bee",3,"c06a9",4,"92ebc",5,"83fcc",6,"90cf4"]}}